apengs_dash_components/__init__.py
apengs_dash_components/com.py
apengs_dash_components/web.py
apengs_dash_components-0.1.0.dist-info/licenses/LICENSE
apengs_dash_components-0.1.0.dist-info/METADATA
apengs_dash_components-0.1.0.dist-info/WHEEL
apengs_dash_components-0.1.0.dist-info/top_level.txt
apengs_dash_components-0.1.0.dist-info/RECORD
